{"timeBegin":1609084800,"timeEnd":1609689599,"new_dies":0,"new_hurts":4079,"new_accidents":2917,"sum_dies":0,"sum_hurts":4079,"sum_accidents":2917,"city":{"\u81fa\u5357\u5e02":{"accidents":318,"dies":0,"hurts":455},"\u81fa\u6771\u7e23":{"accidents":62,"dies":0,"hurts":69},"\u81fa\u4e2d\u5e02":{"accidents":327,"dies":0,"hurts":460},"\u5c4f\u6771\u7e23":{"accidents":154,"dies":0,"hurts":217},"\u6843\u5712\u5e02":{"accidents":359,"dies":0,"hurts":500},"\u82d7\u6817\u7e23":{"accidents":58,"dies":0,"hurts":81},"\u5609\u7fa9\u5e02":{"accidents":24,"dies":0,"hurts":29},"\u81fa\u5317\u5e02":{"accidents":168,"dies":0,"hurts":238},"\u9ad8\u96c4\u5e02":{"accidents":353,"dies":0,"hurts":523},"\u82b1\u84ee\u7e23":{"accidents":51,"dies":0,"hurts":73},"\u65b0\u7af9\u7e23":{"accidents":74,"dies":0,"hurts":101},"\u5f70\u5316\u7e23":{"accidents":199,"dies":0,"hurts":268},"\u65b0\u5317\u5e02":{"accidents":371,"dies":0,"hurts":540},"\u96f2\u6797\u7e23":{"accidents":91,"dies":0,"hurts":115},"\u5b9c\u862d\u7e23":{"accidents":65,"dies":0,"hurts":88},"\u6f8e\u6e56\u7e23":{"accidents":10,"dies":0,"hurts":16},"\u65b0\u7af9\u5e02":{"accidents":48,"dies":0,"hurts":69},"\u5357\u6295\u7e23":{"accidents":77,"dies":0,"hurts":91},"\u5609\u7fa9\u7e23":{"accidents":77,"dies":0,"hurts":104},"\u57fa\u9686\u5e02":{"accidents":25,"dies":0,"hurts":33},"\u91d1\u9580\u7e23":{"accidents":6,"dies":0,"hurts":9}}}