{"timeBegin":1654444800,"timeEnd":1655049599,"new_dies":29,"new_hurts":5753,"new_accidents":4475,"sum_dies":813,"sum_hurts":207715,"sum_accidents":156536,"city":{"\u5f70\u5316\u7e23":{"accidents":354,"dies":6,"hurts":443},"\u81fa\u5357\u5e02":{"accidents":94,"dies":4,"hurts":118},"\u6843\u5712\u5e02":{"accidents":404,"dies":3,"hurts":504},"\u9ad8\u96c4\u5e02":{"accidents":516,"dies":2,"hurts":681},"\u82b1\u84ee\u7e23":{"accidents":19,"dies":2,"hurts":20},"\u5b9c\u862d\u7e23":{"accidents":91,"dies":2,"hurts":118},"\u5357\u6295\u7e23":{"accidents":120,"dies":2,"hurts":152},"\u65b0\u7af9\u7e23":{"accidents":181,"dies":1,"hurts":219},"\u65b0\u7af9\u5e02":{"accidents":157,"dies":1,"hurts":198},"\u81fa\u6771\u7e23":{"accidents":71,"dies":1,"hurts":80},"\u81fa\u5317\u5e02":{"accidents":415,"dies":1,"hurts":531},"\u82d7\u6817\u7e23":{"accidents":110,"dies":1,"hurts":151},"\u5609\u7fa9\u7e23":{"accidents":114,"dies":1,"hurts":153},"\u81fa\u4e2d\u5e02":{"accidents":638,"dies":1,"hurts":828},"\u96f2\u6797\u7e23":{"accidents":87,"dies":1,"hurts":109},"\u65b0\u5317\u5e02":{"accidents":838,"dies":0,"hurts":1095},"\u5c4f\u6771\u7e23":{"accidents":114,"dies":0,"hurts":158},"\u57fa\u9686\u5e02":{"accidents":76,"dies":0,"hurts":99},"\u6f8e\u6e56\u7e23":{"accidents":16,"dies":0,"hurts":21},"\u5609\u7fa9\u5e02":{"accidents":60,"dies":0,"hurts":75}}}