{"timeBegin":1632067200,"timeEnd":1632671999,"new_dies":36,"new_hurts":8143,"new_accidents":6017,"sum_dies":1353,"sum_hurts":334452,"sum_accidents":251432,"city":{"\u6843\u5712\u5e02":{"accidents":843,"dies":7,"hurts":1147},"\u65b0\u5317\u5e02":{"accidents":699,"dies":5,"hurts":961},"\u81fa\u5357\u5e02":{"accidents":771,"dies":3,"hurts":1010},"\u9ad8\u96c4\u5e02":{"accidents":639,"dies":3,"hurts":918},"\u5f70\u5316\u7e23":{"accidents":398,"dies":3,"hurts":527},"\u82b1\u84ee\u7e23":{"accidents":113,"dies":2,"hurts":152},"\u5c4f\u6771\u7e23":{"accidents":290,"dies":2,"hurts":411},"\u96f2\u6797\u7e23":{"accidents":120,"dies":2,"hurts":164},"\u81fa\u4e2d\u5e02":{"accidents":701,"dies":2,"hurts":941},"\u5609\u7fa9\u7e23":{"accidents":160,"dies":2,"hurts":206},"\u65b0\u7af9\u5e02":{"accidents":156,"dies":1,"hurts":208},"\u81fa\u5317\u5e02":{"accidents":424,"dies":1,"hurts":569},"\u5357\u6295\u7e23":{"accidents":144,"dies":1,"hurts":180},"\u81fa\u6771\u7e23":{"accidents":71,"dies":1,"hurts":81},"\u5b9c\u862d\u7e23":{"accidents":2,"dies":1,"hurts":1},"\u65b0\u7af9\u7e23":{"accidents":188,"dies":0,"hurts":255},"\u57fa\u9686\u5e02":{"accidents":84,"dies":0,"hurts":129},"\u82d7\u6817\u7e23":{"accidents":133,"dies":0,"hurts":176},"\u91d1\u9580\u7e23":{"accidents":13,"dies":0,"hurts":17},"\u5609\u7fa9\u5e02":{"accidents":53,"dies":0,"hurts":69},"\u6f8e\u6e56\u7e23":{"accidents":15,"dies":0,"hurts":21}}}