{"timeBegin":1623600000,"timeEnd":1624204799,"new_dies":0,"new_hurts":6732,"new_accidents":5127,"sum_dies":0,"sum_hurts":224290,"sum_accidents":166958,"city":{"\u5c4f\u6771\u7e23":{"accidents":186,"dies":0,"hurts":259},"\u6843\u5712\u5e02":{"accidents":722,"dies":0,"hurts":931},"\u81fa\u4e2d\u5e02":{"accidents":702,"dies":0,"hurts":903},"\u9ad8\u96c4\u5e02":{"accidents":758,"dies":0,"hurts":1009},"\u81fa\u6771\u7e23":{"accidents":47,"dies":0,"hurts":58},"\u65b0\u7af9\u7e23":{"accidents":139,"dies":0,"hurts":179},"\u65b0\u5317\u5e02":{"accidents":588,"dies":0,"hurts":800},"\u81fa\u5357\u5e02":{"accidents":530,"dies":0,"hurts":697},"\u82b1\u84ee\u7e23":{"accidents":77,"dies":0,"hurts":106},"\u57fa\u9686\u5e02":{"accidents":59,"dies":0,"hurts":77},"\u5357\u6295\u7e23":{"accidents":101,"dies":0,"hurts":125},"\u5f70\u5316\u7e23":{"accidents":296,"dies":0,"hurts":389},"\u5b9c\u862d\u7e23":{"accidents":102,"dies":0,"hurts":142},"\u5609\u7fa9\u7e23":{"accidents":92,"dies":0,"hurts":120},"\u96f2\u6797\u7e23":{"accidents":142,"dies":0,"hurts":173},"\u5609\u7fa9\u5e02":{"accidents":64,"dies":0,"hurts":79},"\u82d7\u6817\u7e23":{"accidents":92,"dies":0,"hurts":115},"\u65b0\u7af9\u5e02":{"accidents":131,"dies":0,"hurts":163},"\u6f8e\u6e56\u7e23":{"accidents":10,"dies":0,"hurts":12},"\u81fa\u5317\u5e02":{"accidents":279,"dies":0,"hurts":382},"\u91d1\u9580\u7e23":{"accidents":9,"dies":0,"hurts":12},"\u9023\u6c5f\u7e23":{"accidents":1,"dies":0,"hurts":1}}}