{"timeBegin":1624809600,"timeEnd":1625414399,"new_dies":40,"new_hurts":13601,"new_accidents":10240,"sum_dies":962,"sum_hurts":475316,"sum_accidents":354887,"city":{"\u81fa\u4e2d\u5e02":{"accidents":1405,"dies":7,"hurts":1853},"\u81fa\u5357\u5e02":{"accidents":1193,"dies":5,"hurts":1576},"\u5c4f\u6771\u7e23":{"accidents":368,"dies":5,"hurts":514},"\u96f2\u6797\u7e23":{"accidents":272,"dies":4,"hurts":338},"\u6843\u5712\u5e02":{"accidents":1331,"dies":3,"hurts":1749},"\u5f70\u5316\u7e23":{"accidents":625,"dies":3,"hurts":769},"\u81fa\u6771\u7e23":{"accidents":103,"dies":2,"hurts":124},"\u65b0\u5317\u5e02":{"accidents":1166,"dies":2,"hurts":1610},"\u82d7\u6817\u7e23":{"accidents":164,"dies":2,"hurts":212},"\u5609\u7fa9\u5e02":{"accidents":121,"dies":1,"hurts":157},"\u81fa\u5317\u5e02":{"accidents":597,"dies":1,"hurts":804},"\u57fa\u9686\u5e02":{"accidents":123,"dies":1,"hurts":166},"\u9ad8\u96c4\u5e02":{"accidents":1341,"dies":1,"hurts":1858},"\u5b9c\u862d\u7e23":{"accidents":237,"dies":1,"hurts":320},"\u5357\u6295\u7e23":{"accidents":201,"dies":1,"hurts":268},"\u65b0\u7af9\u5e02":{"accidents":247,"dies":1,"hurts":329},"\u65b0\u7af9\u7e23":{"accidents":340,"dies":0,"hurts":448},"\u5609\u7fa9\u7e23":{"accidents":208,"dies":0,"hurts":266},"\u82b1\u84ee\u7e23":{"accidents":148,"dies":0,"hurts":176},"\u6f8e\u6e56\u7e23":{"accidents":12,"dies":0,"hurts":20},"\u9023\u6c5f\u7e23":{"accidents":6,"dies":0,"hurts":6},"\u91d1\u9580\u7e23":{"accidents":32,"dies":0,"hurts":38}}}