{"timeBegin":1612108800,"timeEnd":1612713599,"new_dies":51,"new_hurts":22069,"new_accidents":16393,"sum_dies":215,"sum_hurts":109095,"sum_accidents":81985,"city":{"\u81fa\u5357\u5e02":{"accidents":2017,"dies":14,"hurts":2684},"\u65b0\u5317\u5e02":{"accidents":2200,"dies":4,"hurts":3015},"\u5609\u7fa9\u7e23":{"accidents":324,"dies":4,"hurts":457},"\u96f2\u6797\u7e23":{"accidents":448,"dies":4,"hurts":594},"\u9ad8\u96c4\u5e02":{"accidents":1728,"dies":4,"hurts":2430},"\u5f70\u5316\u7e23":{"accidents":1141,"dies":4,"hurts":1483},"\u81fa\u5317\u5e02":{"accidents":1227,"dies":3,"hurts":1651},"\u6843\u5712\u5e02":{"accidents":1953,"dies":3,"hurts":2624},"\u5357\u6295\u7e23":{"accidents":362,"dies":2,"hurts":472},"\u82b1\u84ee\u7e23":{"accidents":274,"dies":2,"hurts":373},"\u82d7\u6817\u7e23":{"accidents":354,"dies":2,"hurts":474},"\u81fa\u4e2d\u5e02":{"accidents":1728,"dies":2,"hurts":2331},"\u5c4f\u6771\u7e23":{"accidents":667,"dies":1,"hurts":912},"\u65b0\u7af9\u7e23":{"accidents":577,"dies":1,"hurts":732},"\u5b9c\u862d\u7e23":{"accidents":377,"dies":1,"hurts":499},"\u5609\u7fa9\u5e02":{"accidents":100,"dies":0,"hurts":134},"\u57fa\u9686\u5e02":{"accidents":206,"dies":0,"hurts":286},"\u91d1\u9580\u7e23":{"accidents":30,"dies":0,"hurts":38},"\u65b0\u7af9\u5e02":{"accidents":500,"dies":0,"hurts":676},"\u6f8e\u6e56\u7e23":{"accidents":24,"dies":0,"hurts":30},"\u81fa\u6771\u7e23":{"accidents":154,"dies":0,"hurts":172},"\u9023\u6c5f\u7e23":{"accidents":2,"dies":0,"hurts":2}}}